autopc/__init__.py
autopc/basic/__init__.py
autopc/basic/basic_adb.py
autopc/basic/basic_airtest.py
autopc/basic/basic_opencv.py
autopc/utils/__init__.py
autopc/utils/utils_encoding.py
autopc/utils/utils_logger.py
autopc/utils/utils_version.py
autopc-1.0.1.9.dist-info/LICENSE
autopc-1.0.1.9.dist-info/METADATA
autopc-1.0.1.9.dist-info/WHEEL
autopc-1.0.1.9.dist-info/top_level.txt
autopc-1.0.1.9.dist-info/RECORD
