Metadata-Version: 2.1
Name: autopc
Version: 1.0.1.9
Summary: An image recognition framework running on a computer
Home-page: https://github.com/orcakill/autopc
Author: orcakill
Author-email: orcakill@dingtalk.com
License: Apache License 2.0
Keywords: automation,opencv-python,ocr
Classifier: Programming Language :: Python :: 3.9
License-File: LICENSE
Requires-Dist: airtest ==1.3.5
Requires-Dist: alabaster ==0.7.16
Requires-Dist: annotated-types ==0.7.0
Requires-Dist: asttokens ==3.0.0
Requires-Dist: attrs ==24.3.0
Requires-Dist: babel ==2.16.0
Requires-Dist: backcall ==0.2.0
Requires-Dist: backports.tarfile ==1.2.0
Requires-Dist: beautifulsoup4 ==4.12.3
Requires-Dist: bleach ==6.2.0
Requires-Dist: cached-property ==1.5.2
Requires-Dist: certifi ==2024.8.30
Requires-Dist: chardet ==5.2.0
Requires-Dist: charset-normalizer ==3.3.2
Requires-Dist: click ==8.1.7
Requires-Dist: colorama ==0.4.6
Requires-Dist: colored ==2.2.4
Requires-Dist: commonmark ==0.9.1
Requires-Dist: comtypes ==1.4.7
Requires-Dist: construct ==2.10.70
Requires-Dist: decorator ==5.1.1
Requires-Dist: defusedxml ==0.7.1
Requires-Dist: Deprecated ==1.2.14
Requires-Dist: deprecation ==2.1.0
Requires-Dist: docopt ==0.6.2
Requires-Dist: docutils ==0.21.2
Requires-Dist: executing ==2.1.0
Requires-Dist: facebook-wda ==1.4.9
Requires-Dist: fastjsonschema ==2.21.1
Requires-Dist: ffmpeg-python ==0.2.0
Requires-Dist: filelock ==3.16.1
Requires-Dist: future ==1.0.0
Requires-Dist: idna ==3.10
Requires-Dist: imageio ==2.35.1
Requires-Dist: imagesize ==1.4.1
Requires-Dist: importlib-metadata ==8.0.0
Requires-Dist: ipython ==8.12.3
Requires-Dist: jaraco.classes ==3.4.0
Requires-Dist: jaraco.context ==5.3.0
Requires-Dist: jaraco.functools ==4.0.1
Requires-Dist: jedi ==0.19.2
Requires-Dist: Jinja2 ==3.1.4
Requires-Dist: jsonschema ==4.23.0
Requires-Dist: jsonschema-specifications ==2024.10.1
Requires-Dist: jupyter-client ==8.6.3
Requires-Dist: jupyter-core ==5.7.2
Requires-Dist: jupyterlab-pygments ==0.3.0
Requires-Dist: keyring ==25.4.1
Requires-Dist: loguru ==0.7.3
Requires-Dist: logzero ==1.7.0
Requires-Dist: Markdown ==3.7
Requires-Dist: markdown-it-py ==3.0.0
Requires-Dist: MarkupSafe ==2.1.5
Requires-Dist: matplotlib-inline ==0.1.7
Requires-Dist: mdurl ==0.1.2
Requires-Dist: mistune ==3.0.2
Requires-Dist: mock ==5.1.0
Requires-Dist: more-itertools ==10.3.0
Requires-Dist: mss ==6.1.0
Requires-Dist: nbclient ==0.10.2
Requires-Dist: nbconvert ==7.16.4
Requires-Dist: nbformat ==5.10.4
Requires-Dist: nh3 ==0.2.18
Requires-Dist: numpy ==1.26.4
Requires-Dist: opencv-contrib-python ==4.5.5.64
Requires-Dist: opencv-python ==4.5.5.64
Requires-Dist: packaging ==24.1
Requires-Dist: pandocfilters ==1.5.1
Requires-Dist: parso ==0.8.4
Requires-Dist: pickleshare ==0.7.5
Requires-Dist: pillow ==10.4.0
Requires-Dist: pipreqs ==0.5.0
Requires-Dist: pkginfo ==1.10.0
Requires-Dist: platformdirs ==4.2.2
Requires-Dist: prompt-toolkit ==3.0.48
Requires-Dist: psutil ==6.0.0
Requires-Dist: pure-eval ==0.2.3
Requires-Dist: py ==1.11.0
Requires-Dist: pydantic ==2.9.2
Requires-Dist: pydantic-core ==2.23.4
Requires-Dist: Pygments ==2.18.0
Requires-Dist: python-dateutil ==2.9.0.post0
Requires-Dist: pywin32-ctypes ==0.2.3
Requires-Dist: pywinauto ==0.6.3
Requires-Dist: pyzmq ==26.2.0
Requires-Dist: readme-renderer ==44.0
Requires-Dist: recommonmark ==0.7.1
Requires-Dist: referencing ==0.35.1
Requires-Dist: requests ==2.32.3
Requires-Dist: requests-toolbelt ==1.0.0
Requires-Dist: retry ==0.9.2
Requires-Dist: rfc3986 ==2.0.0
Requires-Dist: rich ==13.9.1
Requires-Dist: rpds-py ==0.22.3
Requires-Dist: rstcheck ==6.2.4
Requires-Dist: rstcheck-core ==1.2.1
Requires-Dist: shellingham ==1.5.4
Requires-Dist: simple-tornado ==0.2.2
Requires-Dist: simplejson ==3.19.3
Requires-Dist: six ==1.16.0
Requires-Dist: snowballstemmer ==2.2.0
Requires-Dist: soupsieve ==2.6
Requires-Dist: Sphinx ==7.4.7
Requires-Dist: sphinx-markdown-tables ==0.0.17
Requires-Dist: sphinx-rtd-theme ==3.0.1
Requires-Dist: sphinxcontrib-applehelp ==2.0.0
Requires-Dist: sphinxcontrib-devhelp ==2.0.0
Requires-Dist: sphinxcontrib-htmlhelp ==2.1.0
Requires-Dist: sphinxcontrib-jquery ==4.1
Requires-Dist: sphinxcontrib-jsmath ==1.0.1
Requires-Dist: sphinxcontrib-qthelp ==2.0.0
Requires-Dist: sphinxcontrib-serializinghtml ==2.0.0
Requires-Dist: stack-data ==0.6.3
Requires-Dist: tabulate ==0.9.0
Requires-Dist: tidevice ==0.12.10
Requires-Dist: tinycss2 ==1.4.0
Requires-Dist: tomli ==2.0.1
Requires-Dist: tornado ==6.4.2
Requires-Dist: traitlets ==5.14.3
Requires-Dist: twine ==5.1.1
Requires-Dist: typer ==0.13.0
Requires-Dist: typing-extensions ==4.12.2
Requires-Dist: urllib3 ==2.2.3
Requires-Dist: wcwidth ==0.2.13
Requires-Dist: webencodings ==0.5.1
Requires-Dist: win32-setctime ==1.2.0
Requires-Dist: wrapt ==1.16.0
Requires-Dist: yarg ==0.1.9
Requires-Dist: zipp ==3.19.2
Requires-Dist: pywin32
Provides-Extra: docs
Requires-Dist: sphinx ; extra == 'docs'
Requires-Dist: recommonmark ; extra == 'docs'
Requires-Dist: sphinx-rtd-theme ; extra == 'docs'
Requires-Dist: mock ; extra == 'docs'
Provides-Extra: test
Requires-Dist: nose ; extra == 'test'
